some_ascii_arts/__init__.py
some_ascii_arts/main.py
some_ascii_arts/utils.py
some_ascii_arts-0.0.1.dist-info/METADATA
some_ascii_arts-0.0.1.dist-info/WHEEL
some_ascii_arts-0.0.1.dist-info/entry_points.txt
some_ascii_arts-0.0.1.dist-info/top_level.txt
some_ascii_arts-0.0.1.dist-info/RECORD
