Metadata-Version: 2.2
Name: some_ascii_arts
Version: 0.0.1
Summary: Display some ASCII arts
